odoo8_addon_sale_stock_order_import-8.0.1.0.0.99.dev5-nspkg.pth
odoo_addons/sale_stock_order_import/README.rst
odoo_addons/sale_stock_order_import/__init__.py
odoo_addons/sale_stock_order_import/__openerp__.py
odoo_addons/sale_stock_order_import/i18n/sale_stock_order_import.pot
odoo_addons/sale_stock_order_import/static/description/icon.png
odoo_addons/sale_stock_order_import/wizard/__init__.py
odoo_addons/sale_stock_order_import/wizard/sale_order_import.py
odoo8_addon_sale_stock_order_import-8.0.1.0.0.99.dev5.dist-info/METADATA
odoo8_addon_sale_stock_order_import-8.0.1.0.0.99.dev5.dist-info/WHEEL
odoo8_addon_sale_stock_order_import-8.0.1.0.0.99.dev5.dist-info/namespace_packages.txt
odoo8_addon_sale_stock_order_import-8.0.1.0.0.99.dev5.dist-info/top_level.txt
odoo8_addon_sale_stock_order_import-8.0.1.0.0.99.dev5.dist-info/RECORD
